<?xml version="1.0"?>
<users>
  <user>
    <uname>siam</uname>
    <pass>1234</pass>
    <level>admin</level>
  </user>
  <user>
    <uname>new</uname>
    <pass>1234</pass>
    <level>user</level>
  </user>
  <user>
    <uname>okay</uname>
    <pass>1234</pass>
    <level>user</level>
  </user>
  <user>
    <uname>john</uname>
    <pass>1234</pass>
    <level>user</level>
  </user>
  <user>
    <uname>mia</uname>
    <pass>1234</pass>
    <level>user</level>
  </user>
  <user>
    <uname>john2</uname>
    <pass>1234</pass>
    <level>user</level>
  </user>
  <user>
    <uname>ami</uname>
    <pass>abc</pass>
    <level>user</level>
  </user>
  <user>
    <uname>abcdef</uname>
    <pass>1234</pass>
    <level>admin</level>
  </user>
</users>
